setup.py
wikimon/__init__.py
wikimon/monitor_geolite2.py
wikimon/monitor_websocket.py
wikimon/parsers.py
wikimon/test_monitor_websocket.py
wikimon/test_parsers.py
wikimon.egg-info/PKG-INFO
wikimon.egg-info/SOURCES.txt
wikimon.egg-info/dependency_links.txt
wikimon.egg-info/not-zip-safe
wikimon.egg-info/pbr.json
wikimon.egg-info/requires.txt
wikimon.egg-info/top_level.txt