Metadata-Version: 1.1
Name: wikimon
Version: 0.6.1
Summary: A WebSocket-oriented monitor for streaming live changes toWikipedia. (also, wikimon, wikital monsters)
Home-page: https://github.com/hatnote/wikimon
Author: Mahmoud Hashemi and Stephen LaPorte
Author-email: mahmoudrhashemi@gmail.com
License: GPLv3
Platform: any
Classifier: Programming Language :: Python :: 2.6
Classifier: Programming Language :: Python :: 2.7
